Metadata-Version: 2.1
Name: batch-face
Version: 1.5.4
Summary: Batch Face Preprocessing for Modern Research
Home-page: https://github.com/elliottzheng/batch-face
Author: Elliott Zheng
Author-email: admin@hypercube.top
License: MIT
Project-URL: Documentation, https://github.com/elliottzheng/batch-face
Project-URL: Source, https://github.com/elliottzheng/batch-face
Project-URL: Tracker, https://github.com/elliottzheng/batch-face/issues
Keywords: face-detection pytorch RetinaFace face-alignment
License-File: LICENSE
Requires-Dist: numpy
Requires-Dist: torch
Requires-Dist: torchvision
Requires-Dist: opencv-python
Requires-Dist: opencv-transforms
Requires-Dist: sixdrepnet
